ofxstatement_be_kbc-0.2.0-nspkg.pth
ofxstatement/plugins/kbcbe.py
ofxstatement_be_kbc-0.2.0.dist-info/LICENSE
ofxstatement_be_kbc-0.2.0.dist-info/METADATA
ofxstatement_be_kbc-0.2.0.dist-info/WHEEL
ofxstatement_be_kbc-0.2.0.dist-info/entry_points.txt
ofxstatement_be_kbc-0.2.0.dist-info/namespace_packages.txt
ofxstatement_be_kbc-0.2.0.dist-info/top_level.txt
ofxstatement_be_kbc-0.2.0.dist-info/zip-safe
ofxstatement_be_kbc-0.2.0.dist-info/RECORD
