Metadata-Version: 2.1
Name: ofxstatement-be-kbc
Version: 0.2.0
Summary: ofxstatement plugin for parsing Belgian KBC bank's CSV statements to OFX
Home-page: https://github.com/plenaerts/ofxstatement-be-kbc
Author: Pieter Lenaerts
Author-email: pieter.aj.lenaerts@gmail.com
License: GPLv3
Keywords: ofx,banking,statement,kbc,csv
Platform: UNKNOWN
Classifier: Development Status :: 5 - Production/Stable
Classifier: Programming Language :: Python :: 3
Classifier: Natural Language :: English
Classifier: Topic :: Office/Business :: Financial :: Accounting
Classifier: Topic :: Utilities
Classifier: Environment :: Console
Classifier: Operating System :: OS Independent
Classifier: License :: OSI Approved :: GNU General Public License v3 (GPLv3)
Requires-Dist: ofxstatement
